<Category name='templatemontecarlo'>
  <description>functions and methods for template based MC simulation.</description>
  <displayName>Template Quasi Gaussain Model</displayName>
  <xlFunctionWizardCategory>QuantLib - Financial</xlFunctionWizardCategory>
  <serializationIncludes>
    <include>qlo/conversions/coercetermstructure.hpp</include>
    <include>qlo/baseinstruments.hpp</include>
    <include>qlo/termstructures.hpp</include>
    <include>qlo/pricingengines.hpp</include>
    <include>qlo/bonds.hpp</include>
    <include>qlo/swaption.hpp</include>
    <include>qlo/schedule.hpp</include>    
    <include>qlo/templatemontecarlo.hpp</include>
  </serializationIncludes>
  <addinIncludes>
    <include>qlo/handleimpl.hpp</include>
    <include>qlo/conversions/coercetermstructure.hpp</include>
    <include>qlo/baseinstruments.hpp</include>
    <include>qlo/termstructures.hpp</include>
    <include>qlo/pricingengines.hpp</include>
    <include>qlo/bonds.hpp</include>
    <include>qlo/swaption.hpp</include>
    <include>qlo/schedule.hpp</include>
    <include>qlo/templatemontecarlo.hpp</include>
  </addinIncludes>
  <copyright>
    Copyright (C) 2015, Sebastian Schlenkrich
  </copyright>
  <Functions>

    <!-- Constructor(s) for RealMCSimulation -->

    <Constructor name='qlRealMCSimulation'>
      <libraryFunction>RealMCSimulation</libraryFunction>
      <SupportedPlatforms>
        <SupportedPlatform name='Excel'/>
        <SupportedPlatform name='Cpp'/>
      </SupportedPlatforms>
      <ParameterList>
        <Parameters>
          <Parameter name='ProcessOrModel' >
            <type>QuantLib::RealStochasticProcess</type>
            <tensorRank>scalar</tensorRank>
            <description>reference to process or model.</description>
          </Parameter>
          <Parameter name='SimTimes' exampleValue='5, 10, ...'>
            <type>QuantLib::Time</type>
            <tensorRank>vector</tensorRank>
            <description>vector of time-grid for SDE integration (in year fractions)</description>
          </Parameter>
          <Parameter name='ObsTimes' exampleValue='5, 10, ...'>
            <type>QuantLib::Time</type>
            <tensorRank>vector</tensorRank>
            <description>vector of time-grid for process observation (in year fractions)</description>
          </Parameter>
          <Parameter name='NPaths' exampleValue ='1024' default='1024' >
            <type>QuantLib::Size</type>
            <tensorRank>scalar</tensorRank>
            <description>number of MC paths.</description>
          </Parameter>
          <Parameter name='ZcbObservTimes' exampleValue='5, 10, ...'>
            <type>QuantLib::Time</type>
            <tensorRank>vector</tensorRank>
            <description>vector of time-grid for zcb adjuster (in year fractions)</description>
          </Parameter>
          <Parameter name='ZcbOffsetTimes' exampleValue='5, 10, ...'>
            <type>QuantLib::Time</type>
            <tensorRank>vector</tensorRank>
            <description>vector of time-grid for zcb adjuster (in year fractions)</description>
          </Parameter>
          <Parameter name='Seed' exampleValue ='1234' default='1234' >
            <type>QuantLib::Size</type>
            <tensorRank>scalar</tensorRank>
            <description>MC seed.</description>
          </Parameter>
          <Parameter name='RichardsonExtrapolation' exampleValue ='true' default='true'>
            <type>bool</type>
            <tensorRank>scalar</tensorRank>
            <description>use Richardson extrapolation (true or false).</description>
          </Parameter>
          <Parameter name='TimeInterpolation' exampleValue ='true' default='true'>
            <type>bool</type>
             <tensorRank>scalar</tensorRank>
            <description>allow time-interpolation for payoff evaluation on simulated paths (true or false).</description>
          </Parameter>
          <Parameter name='StoreBrownians' exampleValue ='false' default='false'>
            <type>bool</type>
            <tensorRank>scalar</tensorRank>
            <description>store Brownian motion increments (true or false).</description>
          </Parameter>
        </Parameters>
      </ParameterList>
    </Constructor>

    <!-- Run simulation with RealMCSimulation -->

    <Member name='qlRealMCSimulationSimulate' type='QuantLib::RealMCSimulation' >
      <description>Simulate MC paths.</description>
      <libraryFunction>simulate</libraryFunction>
      <SupportedPlatforms>
        <!--SupportedPlatform name='Excel' calcInWizard='false'/-->
        <SupportedPlatform name='Excel'/>
        <!--SupportedPlatform name='Calc'/-->
        <!--SupportedPlatform name='Cpp'/-->
      </SupportedPlatforms>
      <ParameterList>
        <Parameters/>
      </ParameterList>
      <ReturnValue>
        <type>void</type>
        <tensorRank>scalar</tensorRank>
      </ReturnValue>
    </Member>

    <!-- Inspectors for RealMCSimulation -->

    <Member name='qlRealMCSimulationSimTimes' type='QuantLib::RealMCSimulation' >
      <description>Returns simulation times.</description>
      <libraryFunction>simTimes</libraryFunction>
      <SupportedPlatforms>
        <!--SupportedPlatform name='Excel' calcInWizard='false'/-->
        <SupportedPlatform name='Excel'/>
        <!--SupportedPlatform name='Calc'/-->
        <!--SupportedPlatform name='Cpp'/-->
      </SupportedPlatforms>
      <ParameterList>
        <Parameters/>
      </ParameterList>
      <ReturnValue>
        <type>QuantLib::Time</type>
        <tensorRank>vector</tensorRank>
      </ReturnValue>
    </Member>

    <Member name='qlRealMCSimulationObsTimes' type='QuantLib::RealMCSimulation' >
      <description>Returns observation times.</description>
      <libraryFunction>obsTimes</libraryFunction>
      <SupportedPlatforms>
        <!--SupportedPlatform name='Excel' calcInWizard='false'/-->
        <SupportedPlatform name='Excel'/>
        <!--SupportedPlatform name='Calc'/-->
        <!--SupportedPlatform name='Cpp'/-->
      </SupportedPlatforms>
      <ParameterList>
        <Parameters/>
      </ParameterList>
      <ReturnValue>
        <type>QuantLib::Time</type>
        <tensorRank>vector</tensorRank>
      </ReturnValue>
    </Member>

    <Member name='qlRealMCSimulationNPaths' type='QuantLib::RealMCSimulation' >
      <description>Returns number of MC paths.</description>
      <libraryFunction>nPaths</libraryFunction>
      <SupportedPlatforms>
        <!--SupportedPlatform name='Excel' calcInWizard='false'/-->
        <SupportedPlatform name='Excel'/>
        <!--SupportedPlatform name='Calc'/-->
        <!--SupportedPlatform name='Cpp'/-->
      </SupportedPlatforms>
      <ParameterList>
        <Parameters/>
      </ParameterList>
      <ReturnValue>
        <type>QuantLib::Size</type>
        <tensorRank>scalar</tensorRank>
      </ReturnValue>
    </Member>

    <Member name='qlRealMCSimulationBrownian' type='QuantLib::RealMCSimulation' >
      <description>Returns the n-th Brownian increments.</description>
      <libraryFunction>brownian</libraryFunction>
      <SupportedPlatforms>
        <!--SupportedPlatform name='Excel' calcInWizard='false'/-->
        <SupportedPlatform name='Excel'/>
        <!--SupportedPlatform name='Calc'/-->
        <!--SupportedPlatform name='Cpp'/-->
      </SupportedPlatforms>
      <ParameterList>
        <Parameters>
          <Parameter name='N' exampleValue ='0' default='0' >
            <type>QuantLib::Size</type>
            <tensorRank>scalar</tensorRank>
            <description>index of MC path (0 .. nPaths).</description>
          </Parameter>
        </Parameters>
      </ParameterList>
      <ReturnValue>
        <type>QuantLib::Time</type>
        <tensorRank>matrix</tensorRank>
      </ReturnValue>
    </Member>

    <Member name='qlRealMCSimulationPath' type='QuantLib::RealMCSimulation' >
      <description>Returns the n-th MC path.</description>
      <libraryFunction>observedPath</libraryFunction>
      <SupportedPlatforms>
        <!--SupportedPlatform name='Excel' calcInWizard='false'/-->
        <SupportedPlatform name='Excel'/>
        <!--SupportedPlatform name='Calc'/-->
        <!--SupportedPlatform name='Cpp'/-->
      </SupportedPlatforms>
      <ParameterList>
        <Parameters>
          <Parameter name='N' exampleValue ='0' default='0' >
            <type>QuantLib::Size</type>
            <tensorRank>scalar</tensorRank>
            <description>index of MC path (0 .. nPaths).</description>
          </Parameter>
        </Parameters>      
      </ParameterList>
      <ReturnValue>
        <type>QuantLib::Time</type>
        <tensorRank>matrix</tensorRank>
      </ReturnValue>
    </Member>
    
    <!-- ZCB adjuster calculation and inspectors -->
    
    <Member name='qlRealMCSimulationCalcZCBAdjuster' type='QuantLib::RealMCSimulation' >
      <description>calculate the ZCB adjuster matrix for given simulation.</description>
      <libraryFunction>calculateZCBAdjuster</libraryFunction>
      <SupportedPlatforms>
        <!--SupportedPlatform name='Excel' calcInWizard='false'/-->
        <SupportedPlatform name='Excel'/>
        <!--SupportedPlatform name='Calc'/-->
        <!--SupportedPlatform name='Cpp'/-->
      </SupportedPlatforms>
      <ParameterList>
        <Parameters/>
      </ParameterList>
      <ReturnValue>
        <type>void</type>
        <tensorRank>scalar</tensorRank>
      </ReturnValue>
    </Member>

    <Member name='qlRealMCSimulationZCBAdjuster' type='QuantLib::RealMCSimulation' >
      <description>Returns the zcb adjuster matrix.</description>
      <libraryFunction>zcbAdjuster</libraryFunction>
      <SupportedPlatforms>
        <!--SupportedPlatform name='Excel' calcInWizard='false'/-->
        <SupportedPlatform name='Excel'/>
        <!--SupportedPlatform name='Calc'/-->
        <!--SupportedPlatform name='Cpp'/-->
      </SupportedPlatforms>
      <ParameterList>
        <Parameters/>
      </ParameterList>
      <ReturnValue>
        <type>QuantLib::Time</type>
        <tensorRank>matrix</tensorRank>
      </ReturnValue>
    </Member>

    <Member name='qlRealMCSimulationZCBAdjustertT' type='QuantLib::RealMCSimulation' >
      <description>Returns the zcb adjuster .</description>
      <libraryFunction>zcbAdjuster</libraryFunction>
      <SupportedPlatforms>
        <!--SupportedPlatform name='Excel' calcInWizard='false'/-->
        <SupportedPlatform name='Excel'/>
        <!--SupportedPlatform name='Calc'/-->
        <!--SupportedPlatform name='Cpp'/-->
      </SupportedPlatforms>
      <ParameterList>
        <Parameters>
          <Parameter name='ObsTime' exampleValue ='1' default='1' >
            <type>QuantLib::Time</type>
            <tensorRank>scalar</tensorRank>
            <description>zcb observation time.</description>
          </Parameter>
          <Parameter name='MatTime' exampleValue ='2' default='2' >
            <type>QuantLib::Time</type>
            <tensorRank>scalar</tensorRank>
            <description>zcb maturity time.</description>
          </Parameter>
        </Parameters>
      </ParameterList>
      <ReturnValue>
        <type>QuantLib::Real</type>
        <tensorRank>scalar</tensorRank>
      </ReturnValue>
    </Member>


    <!-- Payoffs and Pricer -->

    <Procedure name='qlRealMCPayoffsNPV' >
      <description>Returns NPV of simulated payoff.</description>
      <alias>QuantLib::RealMCPayoffPricer::NPV</alias>
      <SupportedPlatforms>
        <SupportedPlatform name='Excel'/>
      </SupportedPlatforms>
      <ParameterList>
        <Parameters>
          <Parameter name='Payoffs' >
            <type>QuantLib::RealMCPayoff</type>
            <tensorRank>vector</tensorRank>
            <description>reference to payoffs.</description>
          </Parameter>
          <Parameter name='Simulation' >
            <type>QuantLib::RealMCSimulation</type>
            <tensorRank>scalar</tensorRank>
            <description>reference to RealMCSimulation object.</description>
          </Parameter>
        </Parameters>
      </ParameterList>
      <ReturnValue>
        <type>QuantLib::Real</type>
        <tensorRank>scalar</tensorRank>
      </ReturnValue>
    </Procedure>


    <Constructor name='qlRealMCPayoffPricer'>
      <libraryFunction>RealMCPayoffPricer</libraryFunction>
      <SupportedPlatforms>
        <SupportedPlatform name='Excel'/>
        <SupportedPlatform name='Cpp'/>
      </SupportedPlatforms>
      <ParameterList>
        <Parameters>
          <Parameter name='Payoffs' >
            <type>QuantLib::RealMCPayoff</type>
            <tensorRank>vector</tensorRank>
            <description>reference to payoffs.</description>
          </Parameter>
          <Parameter name='Simulation' >
            <type>QuantLib::RealMCSimulation</type>
            <tensorRank>scalar</tensorRank>
            <description>reference to RealMCSimulation object.</description>
          </Parameter>
        </Parameters>
      </ParameterList>
    </Constructor>

    <Member name='qlRealMCPayoffPricerNPV' type='QuantLib::RealMCPayoffPricer' >
      <description>Returns NPV of simulated payoff.</description>
      <libraryFunction>NPV</libraryFunction>
      <SupportedPlatforms>
        <!--SupportedPlatform name='Excel' calcInWizard='false'/-->
        <SupportedPlatform name='Excel'/>
        <!--SupportedPlatform name='Calc'/-->
        <!--SupportedPlatform name='Cpp'/-->
      </SupportedPlatforms>
      <ParameterList>
        <Parameters/>
      </ParameterList>
      <ReturnValue>
        <type>QuantLib::Real</type>
        <tensorRank>scalar</tensorRank>
      </ReturnValue>
    </Member>

    <Constructor name='qlRealMCCash'>
      <libraryFunction>RealMCCash</libraryFunction>
      <SupportedPlatforms>
        <SupportedPlatform name='Excel'/>
        <SupportedPlatform name='Cpp'/>
      </SupportedPlatforms>
      <ParameterList>
        <Parameters>
          <Parameter name='ObservationTime' exampleValue ='1' default='1' >
            <type>QuantLib::Time</type>
            <tensorRank>scalar</tensorRank>
            <description>observation time (t).</description>
          </Parameter>
          <Parameter name='PayTime' exampleValue ='2' default='2' >
            <type>QuantLib::Time</type>
            <tensorRank>scalar</tensorRank>
            <description>payment time (T).</description>
          </Parameter>
        </Parameters>
      </ParameterList>
    </Constructor>

    <Constructor name='qlRealMCVanillaOption'>
      <libraryFunction>RealMCVanillaOption</libraryFunction>
      <SupportedPlatforms>
        <SupportedPlatform name='Excel'/>
        <SupportedPlatform name='Cpp'/>
      </SupportedPlatforms>
      <ParameterList>
        <Parameters>
          <Parameter name='ObservationTime' exampleValue ='1' default='1' >
            <type>QuantLib::Time</type>
            <tensorRank>scalar</tensorRank>
            <description>observation time (t).</description>
          </Parameter>
          <Parameter name='PayTime' exampleValue ='2' default='2' >
            <type>QuantLib::Time</type>
            <tensorRank>scalar</tensorRank>
            <description>payment time (T).</description>
          </Parameter>
          <Parameter name='Strike' exampleValue ='2' default='2' >
            <type>QuantLib::Real</type>
            <tensorRank>scalar</tensorRank>
            <description>option strike.</description>
          </Parameter>
          <Parameter name='CallOrPut' exampleValue ='2' default='2' >
            <type>QuantLib::Real</type>
            <tensorRank>scalar</tensorRank>
            <description>call (+1) or Put (-1) option.</description>
          </Parameter>
        </Parameters>
      </ParameterList>
    </Constructor>

    <Constructor name='qlRealMCAnnuity'>
      <libraryFunction>RealMCAnnuity</libraryFunction>
      <SupportedPlatforms>
        <SupportedPlatform name='Excel'/>
        <SupportedPlatform name='Cpp'/>
      </SupportedPlatforms>
      <ParameterList>
        <Parameters>
          <Parameter name='ObservationTime' exampleValue ='1' default='1' >
            <type>QuantLib::Time</type>
            <tensorRank>scalar</tensorRank>
            <description>observation time (t).</description>
          </Parameter>
          <Parameter name='PayTimes' >
            <type>QuantLib::Time</type>
            <tensorRank>vector</tensorRank>
            <description>vector of payment times.</description>
          </Parameter>
          <Parameter name='PayWeights' >
            <type>QuantLib::Real</type>
            <tensorRank>vector</tensorRank>
            <description>vector of payment weights (usually year fractions).</description>
          </Parameter>
        </Parameters>
      </ParameterList>
    </Constructor>

    <Constructor name='qlRealMCModelSwaption'>
      <libraryFunction>RealMCModelSwaption</libraryFunction>
      <SupportedPlatforms>
        <SupportedPlatform name='Excel'/>
        <SupportedPlatform name='Cpp'/>
      </SupportedPlatforms>
      <ParameterList>
        <Parameters>
          <Parameter name='ObservationTime' exampleValue ='1' default='1' >
            <type>QuantLib::Time</type>
            <tensorRank>scalar</tensorRank>
            <description>observation time (t).</description>
          </Parameter>
          <Parameter name='Times' >
            <type>QuantLib::Time</type>
            <tensorRank>vector</tensorRank>
            <description>vector of start and payment times.</description>
          </Parameter>
          <Parameter name='PayWeights' >
            <type>QuantLib::Real</type>
            <tensorRank>vector</tensorRank>
            <description>vector of payment weights (usually year fractions).</description>
          </Parameter>
          <Parameter name='StrikeRate' >
            <type>QuantLib::Real</type>
            <tensorRank>scalar</tensorRank>
            <description>strike (or swap fixed) rate.</description>
          </Parameter>
          <Parameter name='PayOrReceive' >
            <type>QuantLib::Real</type>
            <tensorRank>scalar</tensorRank>
            <description>pay (+1) or receive (-1) fixed rate.</description>
          </Parameter>
        </Parameters>
      </ParameterList>
    </Constructor>

    <Constructor name='qlRealMCGeneralSwaption'>
      <libraryFunction>RealMCGeneralSwaption</libraryFunction>
      <SupportedPlatforms>
        <SupportedPlatform name='Excel'/>
        <SupportedPlatform name='Cpp'/>
      </SupportedPlatforms>
      <ParameterList>
        <Parameters>
          <Parameter name='ObservationTime' exampleValue ='1' default='1' >
            <type>QuantLib::Time</type>
            <tensorRank>scalar</tensorRank>
            <description>observation time (t).</description>
          </Parameter>
          <Parameter name='FloatTimes' >
            <type>QuantLib::Time</type>
            <tensorRank>vector</tensorRank>
            <description>vector of float leg payment times.</description>
          </Parameter>
          <Parameter name='FloatWeights' >
            <type>QuantLib::Real</type>
            <tensorRank>vector</tensorRank>
            <description>vector of float leg cash flows (usually 1 and -1).</description>
          </Parameter>
          <Parameter name='FixedTimes' >
            <type>QuantLib::Time</type>
            <tensorRank>vector</tensorRank>
            <description>vector of fixed leg payment times.</description>
          </Parameter>
          <Parameter name='FixedWeights' >
            <type>QuantLib::Real</type>
            <tensorRank>vector</tensorRank>
            <description>vector of fixed leg weights (usually year fractions).</description>
          </Parameter>
          <Parameter name='StrikeRate' >
            <type>QuantLib::Real</type>
            <tensorRank>scalar</tensorRank>
            <description>strike (or swap fixed) rate.</description>
          </Parameter>
          <Parameter name='PayOrReceive' >
            <type>QuantLib::Real</type>
            <tensorRank>scalar</tensorRank>
            <description>pay (+1) or receive (-1) fixed rate.</description>
          </Parameter>
        </Parameters>
      </ParameterList>
    </Constructor>



  </Functions>
</Category>
